pyWinActivate.py
pyWinActivate-1.3.0.dist-info/LICENSE.txt
pyWinActivate-1.3.0.dist-info/METADATA
pyWinActivate-1.3.0.dist-info/WHEEL
pyWinActivate-1.3.0.dist-info/top_level.txt
pyWinActivate-1.3.0.dist-info/RECORD
