Metadata-Version: 2.1
Name: pyWinActivate
Version: 1.3.0
Summary: Activate and focus on any opened window by using the window title.
Home-page: https://github.com/InfiniteNex/pyWinActivate
Author: InfiniteNex
Author-email: InfiniteNex <the_nexus@mail.bg>
Project-URL: Homepage, https://github.com/InfiniteNex/pyWinActivate
Project-URL: Bug Tracker, https://github.com/InfiniteNex/pyWinActivate/issues
Classifier: Programming Language :: Python :: 3
Classifier: License :: OSI Approved :: MIT License
Classifier: Operating System :: OS Independent
Requires-Python: >=3.7
License-File: LICENSE.txt
